homework/mux_16_1/mux_2_1.v
module mux_2_1(a,b,sel,y);
  input [15:0] a,b;
  input sel;
  output [15:0] y;

  assign y = (sel == 1'b0) ? a : b;
endmodule

homework/mux_16_1/mux_8_1.v
module mux_8_1(a,b,c,d,e,f,g,h,sel,y);
  input [15:0] a,b,c,d,e,f,g,h;
  input [2:0] sel;
  output reg [15:0] y;

  always@(y,sel)
  begin
    if(sel == 3'b000) begin
      y = a;
    end
    else if(sel == 3'b001) begin
      y = b;
    end
    else if(sel == 3'b010) begin
      y = c;
    end
    else if(sel == 3'b011) begin
      y = d;
    end
    else if(sel == 3'b100) begin
      y = e;
    end
    else if(sel == 3'b101) begin
      y = f;
    end
    else if(sel == 3'b110) begin
      y = g;
    end
    else if(sel == 3'b111) begin
      y = h;
    end
  end
endmodule

homework/mux_16_1/mux_16_1.v
`include "mux_2_1.v"
`include "mux_8_1.v"

module mux_16_1(a,b,c,d,e,f,g,h,i,j,k,l,m,n,s,o,sel,y);

input [15:0] a,b,c,d,e,f,g,h,i,j,k,l,m,n,s,o;
input [3:0] sel;
output [15:0] y;

wire [15:0] tp1,tp2;


mux_8_1 mux8_1_1(a,b,c,d,e,f,g,h,sel[2:0],tp1);
mux_8_1 mux8_1_2(i,j,k,l,m,n,s,o,sel[2:0],tp2);

mux_2_1 mux_final(tp1,tp2,sel[3],y);

endmodule

homework/mux_16_1/mux_16_1_tb.v
`include "mux_16_1.v"
module mux_16_1_tb();
reg [15:0] a,b,c,d,e,f,g,h,i,j,k,l,m,n,s,o,z;
reg [3:0] sel;
wire [15:0] y;

mux_16_1 mux_16_1(a,b,c,d,e,f,g,h,i,j,k,l,m,n,s,o,sel,y);

initial begin
  $display(" a =", a, " b =", b, " c =", c, " d =", d, " e =", e, " f =", f, " g =", g, " h =", h, " i =", i, " j =", j, " k =", k, " l =", l, " m =", m, " n =", n, " s =" ,s, " o =", o, " sel =", sel, " y =", y);
  $dumpfile("mux_16_1_tb.vcd");
  $dumpvars();
  
  a = 1212; b = 23; c = 0; d = 432;
  e = 51; f = 61; g = 17; h = 38;
  i = 91; j = 140; k = 111; l = 124;
  m = 113; n = 14; s = 155; o = 165;

  for(z = 0; z < 16; ++z) begin
    i = 3;
    sel = z;
    #3
    $display(" a =", a, " b =", b, " c =", c, " d =", d, " e =", e, " f =", f, " g =", g, " h =", h, " i =", i, " j =", j, " k =", k, " l =", l, " m =", m, " n =", n, " s =" ,s, " o =", o, " sel =", sel, " y =", y);
  end
end
endmodule

homework/mux_16_1/mux_16_1_tb.vcd
$date
	Sat Sep 26 00:49:59 2020
$end
$version
	Icarus Verilog
$end
$timescale
	1s
$end
$scope module mux_16_1_tb $end
$var wire 16 ! y [15:0] $end
$var reg 16 " a [15:0] $end
$var reg 16 # b [15:0] $end
$var reg 16 $ c [15:0] $end
$var reg 16 % d [15:0] $end
$var reg 16 & e [15:0] $end
$var reg 16 ' f [15:0] $end
$var reg 16 ( g [15:0] $end
$var reg 16 ) h [15:0] $end
$var reg 16 * i [15:0] $end
$var reg 16 + j [15:0] $end
$var reg 16 , k [15:0] $end
$var reg 16 - l [15:0] $end
$var reg 16 . m [15:0] $end
$var reg 16 / n [15:0] $end
$var reg 16 0 o [15:0] $end
$var reg 16 1 s [15:0] $end
$var reg 4 2 sel [3:0] $end
$var reg 16 3 z [15:0] $end
$scope module mux_16_1 $end
$var wire 16 4 a [15:0] $end
$var wire 16 5 b [15:0] $end
$var wire 16 6 c [15:0] $end
$var wire 16 7 d [15:0] $end
$var wire 16 8 e [15:0] $end
$var wire 16 9 f [15:0] $end
$var wire 16 : g [15:0] $end
$var wire 16 ; h [15:0] $end
$var wire 16 < i [15:0] $end
$var wire 16 = j [15:0] $end
$var wire 16 > k [15:0] $end
$var wire 16 ? l [15:0] $end
$var wire 16 @ m [15:0] $end
$var wire 16 A n [15:0] $end
$var wire 16 B o [15:0] $end
$var wire 16 C s [15:0] $end
$var wire 4 D sel [3:0] $end
$var wire 16 E y [15:0] $end
$var wire 16 F tp2 [15:0] $end
$var wire 16 G tp1 [15:0] $end
$scope module mux8_1_1 $end
$var wire 16 H a [15:0] $end
$var wire 16 I b [15:0] $end
$var wire 16 J c [15:0] $end
$var wire 16 K d [15:0] $end
$var wire 16 L e [15:0] $end
$var wire 16 M f [15:0] $end
$var wire 16 N g [15:0] $end
$var wire 16 O h [15:0] $end
$var wire 3 P sel [2:0] $end
$var reg 16 Q y [15:0] $end
$upscope $end
$scope module mux8_1_2 $end
$var wire 16 R a [15:0] $end
$var wire 16 S b [15:0] $end
$var wire 16 T c [15:0] $end
$var wire 16 U d [15:0] $end
$var wire 16 V e [15:0] $end
$var wire 16 W f [15:0] $end
$var wire 16 X g [15:0] $end
$var wire 16 Y h [15:0] $end
$var wire 3 Z sel [2:0] $end
$var reg 16 [ y [15:0] $end
$upscope $end
$scope module mux_final $end
$var wire 16 \ a [15:0] $end
$var wire 16 ] b [15:0] $end
$var wire 1 ^ sel $end
$var wire 16 _ y [15:0] $end
$upscope $end
$upscope $end
$upscope $end
$enddefinitions $end
#0
$dumpvars
b10010111100 _
0^
b11 ]
b10010111100 \
b11 [
b0 Z
b10100101 Y
b10011011 X
b1110 W
b1110001 V
b1111100 U
b1101111 T
b10001100 S
b11 R
b10010111100 Q
b0 P
b100110 O
b10001 N
b111101 M
b110011 L
b110110000 K
b0 J
b10111 I
b10010111100 H
b10010111100 G
b11 F
b10010111100 E
b0 D
b10011011 C
b10100101 B
b1110 A
b1110001 @
b1111100 ?
b1101111 >
b10001100 =
b11 <
b100110 ;
b10001 :
b111101 9
b110011 8
b110110000 7
b0 6
b10111 5
b10010111100 4
b0 3
b0 2
b10011011 1
b10100101 0
b1110 /
b1110001 .
b1111100 -
b1101111 ,
b10001100 +
b11 *
b100110 )
b10001 (
b111101 '
b110011 &
b110110000 %
b0 $
b10111 #
b10010111100 "
b10010111100 !
$end
#3
b10111 !
b10111 E
b10111 _
b10111 G
b10111 Q
b10111 \
b10001100 F
b10001100 [
b10001100 ]
b1 P
b1 Z
b1 2
b1 D
b1 3
#6
b0 !
b0 E
b0 _
b0 G
b0 Q
b0 \
b1101111 F
b1101111 [
b1101111 ]
b10 P
b10 Z
b10 2
b10 D
b10 3
#9
b110110000 !
b110110000 E
b110110000 _
b110110000 G
b110110000 Q
b110110000 \
b1111100 F
b1111100 [
b1111100 ]
b11 P
b11 Z
b11 2
b11 D
b11 3
#12
b110011 !
b110011 E
b110011 _
b110011 G
b110011 Q
b110011 \
b1110001 F
b1110001 [
b1110001 ]
b100 P
b100 Z
b100 2
b100 D
b100 3
#15
b111101 !
b111101 E
b111101 _
b111101 G
b111101 Q
b111101 \
b1110 F
b1110 [
b1110 ]
b101 P
b101 Z
b101 2
b101 D
b101 3
#18
b10001 !
b10001 E
b10001 _
b10001 G
b10001 Q
b10001 \
b10011011 F
b10011011 [
b10011011 ]
b110 P
b110 Z
b110 2
b110 D
b110 3
#21
b100110 !
b100110 E
b100110 _
b100110 G
b100110 Q
b100110 \
b10100101 F
b10100101 [
b10100101 ]
b111 P
b111 Z
b111 2
b111 D
b111 3
#24
b11 !
b11 E
b11 _
b10010111100 G
b10010111100 Q
b10010111100 \
b11 F
b11 [
b11 ]
b0 P
b0 Z
1^
b1000 2
b1000 D
b1000 3
#27
b10001100 !
b10001100 E
b10001100 _
b10111 G
b10111 Q
b10111 \
b10001100 F
b10001100 [
b10001100 ]
b1 P
b1 Z
b1001 2
b1001 D
b1001 3
#30
b1101111 !
b1101111 E
b1101111 _
b0 G
b0 Q
b0 \
b1101111 F
b1101111 [
b1101111 ]
b10 P
b10 Z
b1010 2
b1010 D
b1010 3
#33
b1111100 !
b1111100 E
b1111100 _
b110110000 G
b110110000 Q
b110110000 \
b1111100 F
b1111100 [
b1111100 ]
b11 P
b11 Z
b1011 2
b1011 D
b1011 3
#36
b1110001 !
b1110001 E
b1110001 _
b110011 G
b110011 Q
b110011 \
b1110001 F
b1110001 [
b1110001 ]
b100 P
b100 Z
b1100 2
b1100 D
b1100 3
#39
b1110 !
b1110 E
b1110 _
b111101 G
b111101 Q
b111101 \
b1110 F
b1110 [
b1110 ]
b101 P
b101 Z
b1101 2
b1101 D
b1101 3
#42
b10011011 !
b10011011 E
b10011011 _
b10001 G
b10001 Q
b10001 \
b10011011 F
b10011011 [
b10011011 ]
b110 P
b110 Z
b1110 2
b1110 D
b1110 3
#45
b10100101 !
b10100101 E
b10100101 _
b100110 G
b100110 Q
b100110 \
b10100101 F
b10100101 [
b10100101 ]
b111 P
b111 Z
b1111 2
b1111 D
b1111 3
#48
b10000 3
