labs/lab3/thunderbird.v
module thunderbird(left, right, reset, clk, out);
  input left, right, reset, clk;
  output reg[5:0] out;
  reg [5:0] state, n_state;

  // outputs
  parameter 
  R = 6'b000000, 
  LA = 6'b001000,
  LBLA = 6'b011000,
  LCLBLA = 6'b111000,
  RA = 6'b000001,
  RBRA = 6'b000011,
  RCRBRA = 6'b000111,
  LR = 6'b111111;

  always @ (posedge clk or negedge reset) 
  begin
    if(reset==1)
      state <= reset;
    else
      state <= n_state;
  end

  always @(right, left, state) 
  begin
    case(state)
      R: begin 
        // si l=0 y r=1 entonces n_state=RA, si l=1 y r=0 entonces n_state=LA, si ambos son 1 entonces n_state=LR
        out=state; if(left==1'b0 && right==1'b1) n_state=RA; else if(left==1'b1 && right==1'b0) n_state=LA; else if(right==1'b1 && left==1'b1) n_state=LR; 
      end
      LA: begin 
        // si r=0 entonces n_state=LBLA, si y r=1 entonces n_state=R
        out=state; if(right==1'b0) n_state=LBLA; else if(right==1'b1) n_state=R;
      end
      LBLA: begin 
        // si r=0 entonces n_state=LCLBLA si r=1 entonces n_state=R
        out=state; if(right==1'b0) n_state=LCLBLA; else if(right==1'b1) n_state=R; 
      end
      LCLBLA: begin 
        // si r=1 y l=0 entonces n_state=RA, si r=0 y l=1 n_state=LA, si ambos están activos entonces n\_state=LR
        out=state; if(left==1'b0 && right==1'b1) n_state=RA; else if(left==1'b1 && right==1'b0) n_state=LA; else if(left==1'b1 && right==1'b1) n_state=LR;
      end
      RA: begin 
        // si l=0 entonces n_state=RBRA, si l=q n_state=R
        out=state; if(left==1'b0) n_state=RBRA; else if(left==1'b1) n_state=R;
      end
      RBRA: begin 
        // si l=0 entonces n_state=RCRBRA, si l=1 entonces n_state=R
        out=state; if(left==1'b0) n_state=RCRBRA; else if(left==1'b1) n_state=R; 
      end
      RCRBRA: begin 
        // si l=0 y r=1 entonces n_state=RA, si l=1 y r=0 entonces n_state=LA, si l=1 y r=1 entonces n_state=LR
        out=state; if(left==1'b0 && right==1'b1) n_state=RA; else if(left==1'b1 && right==1'b0) n_state=LA; else if(right==1'b1 && left==1'b1) n_state=LR;
      end
      LR: begin 
        // si l=0 y r=1 entonces n_state=RA, si l=1 y r=0 entonces n_state=LA
        out=state; if(left==1'b0 && right==1'b1) n_state=RA; else if(left==1'b1 && right==1'b0) n_state=LA;
      end
      default: n_state=R;  
    endcase
  end

endmodule

labs/lab3/thunderbird_tb.v
`timescale 1ns/1ns
`include "thunderbird.v"
module thunderbird_tb();
  reg left, right, reset, clk;
  wire [5:0] out;

  // clock
  initial begin
  clk = 0;
  forever #3 clk = ~clk;
  end

  initial begin
      $monitor("left=%4b,right=%4b,reset=%4b,clk=%4b,out=%4b",left,right,reset,clk,out);
      $dumpfile("thunderbird.vcd");
      $dumpvars;
      reset<=1'b1;right<=1'b0;left<=1'b0;
      #3
      reset<=1'b0;
      #3
      right<=1'b1;left<=1'b0;
      #8
      right<=1'b0;left<=1'b0;
      #8
      right<=1'b0;left<=1'b0;
      #8
      reset<=1'b0;
      #3
      right<=1'b0;left<=1'b1;
      #8
      right<=1'b0;left<=1'b0;
      #8
      right<=1'b0;left<=1'b0;
      #8
      right<=1'b1;left<=1'b1;
      #3
      $finish;
  end

  thunderbird tbird(left, right, reset, clk, out);


endmodule

labs/lab3/thunderbird.vcd
$date
	Wed Nov  4 17:39:32 2020
$end
$version
	Icarus Verilog
$end
$timescale
	1ns
$end
$scope module thunderbird_tb $end
$var wire 6 ! out [5:0] $end
$var reg 1 " clk $end
$var reg 1 # left $end
$var reg 1 $ reset $end
$var reg 1 % right $end
$scope module tbird $end
$var wire 1 " clk $end
$var wire 1 # left $end
$var wire 1 $ reset $end
$var wire 1 % right $end
$var reg 6 & n_state [5:0] $end
$var reg 6 ' out [5:0] $end
$var reg 6 ( state [5:0] $end
$upscope $end
$upscope $end
$enddefinitions $end
#0
$dumpvars
bx (
bx '
b0 &
0%
1$
0#
0"
bx !
$end
#3
b11 &
b0 !
b0 '
b0 (
0$
1"
#6
b1 &
1%
0"
#9
b11 &
b1 !
b1 '
b1 (
1"
#12
0"
#14
0%
#15
b111 &
b11 !
b11 '
b11 (
1"
#18
0"
#21
b111 !
b111 '
b111 (
1"
#24
0"
#27
1"
#30
0"
#33
b1000 &
1#
1"
#36
0"
#39
b11000 &
b1000 !
b1000 '
b1000 (
1"
#41
0#
#42
0"
#45
b111000 &
b11000 !
b11000 '
b11000 (
1"
#48
0"
#51
b111000 !
b111000 '
b111000 (
1"
#54
0"
#57
b111111 &
1#
1%
1"
