homework/bcd/bcd.v
module bcd(x,y);
  input [4:0] x;
  output reg [4:0] y;

  always@ (x,y) begin
    if(x == 4'b0000) begin
      y = 4'b0001;
    end
    else if(x == 4'b0001) begin
      y = 4'b0010;
    end
    else if(x == 4'b0010) begin
      y = 4'b0011;
    end
    else if(x == 4'b0011) begin
      y = 4'b0100;
    end
    else if(x == 4'b0100) begin
      y = 4'b0101;
    end
    else if(x == 4'b0101) begin
      y = 4'b0110;
    end
    else if(x == 4'b0110) begin
      y = 4'b0111;
    end
    else if(x == 4'b0111) begin
      y = 4'b1000;
    end
    else if(x == 4'b1000) begin
      y = 4'b1001;
    end
    else if(x == 4'b1001) begin
      y = 4'b0000;
    end
    else begin
      y = 4'bx;
    end
  end
endmodule

homework/bcd/bcd_tb.v
`timescale 1ns/1ns
`include "bcd.v"

module bcd_tb();
  reg [4:0] x,i;
  wire [4:0] y;

  bcd bcd(x,y);

  initial begin
    $dumpfile("comparador.vcd");
    $dumpvars();
    for(i = 0; i < 12; ++i) begin
      x = i;
      #1
      $display("inp = %b ", x[3:0] ,"\nout = %b ",y[3:0]);
    end
  end
endmodule

homework/bcd/comparador.vcd
$date
	Sat Sep 26 03:09:00 2020
$end
$version
	Icarus Verilog
$end
$timescale
	1ns
$end
$scope module bcd_tb $end
$var wire 5 ! y [4:0] $end
$var reg 5 " i [4:0] $end
$var reg 5 # x [4:0] $end
$scope module bcd $end
$var wire 5 $ x [4:0] $end
$var reg 5 % y [4:0] $end
$upscope $end
$upscope $end
$enddefinitions $end
#0
$dumpvars
b1 %
b0 $
b0 #
b0 "
b1 !
$end
#1
b10 !
b10 %
b1 #
b1 $
b1 "
#2
b11 !
b11 %
b10 #
b10 $
b10 "
#3
b100 !
b100 %
b11 #
b11 $
b11 "
#4
b101 !
b101 %
b100 #
b100 $
b100 "
#5
b110 !
b110 %
b101 #
b101 $
b101 "
#6
b111 !
b111 %
b110 #
b110 $
b110 "
#7
b1000 !
b1000 %
b111 #
b111 $
b111 "
#8
b1001 !
b1001 %
b1000 #
b1000 $
b1000 "
#9
b0 !
b0 %
b1001 #
b1001 $
b1001 "
#10
b0xxxx !
b0xxxx %
b1010 #
b1010 $
b1010 "
#11
b1011 #
b1011 $
b1011 "
#12
b1100 "
